stimulsoft_dashboards/__init__.py
stimulsoft_dashboards/export/StiDashboardExportSettings.py
stimulsoft_dashboards/export/StiDataDashboardExportSettings.py
stimulsoft_dashboards/export/StiExcelDashboardExportSettings.py
stimulsoft_dashboards/export/StiHtmlDashboardExportSettings.py
stimulsoft_dashboards/export/StiImageDashboardExportSettings.py
stimulsoft_dashboards/export/StiPdfDashboardExportSettings.py
stimulsoft_dashboards/export/__init__.py
stimulsoft_dashboards/export/enums/StiDashboardExportFormat.py
stimulsoft_dashboards/export/enums/StiDashboardScaleMode.py
stimulsoft_dashboards/export/enums/__init__.py
stimulsoft_dashboards/report/StiDashboard.py
stimulsoft_dashboards/report/__init__.py
stimulsoft_dashboards/resources/StiResourcesHelper.py
stimulsoft_dashboards/resources/__init__.py
stimulsoft_dashboards/resources/scripts/StiScriptResource.py
stimulsoft_dashboards/resources/scripts/__init__.py
stimulsoft_dashboards/resources/scripts/stimulsoft.dashboards.js
stimulsoft_dashboards/resources/scripts/stimulsoft.dashboards.pack.js
stimulsoft_dashboards-2026.1.2.dist-info/licenses/LICENSE.md
stimulsoft_dashboards-2026.1.2.dist-info/METADATA
stimulsoft_dashboards-2026.1.2.dist-info/WHEEL
stimulsoft_dashboards-2026.1.2.dist-info/top_level.txt
stimulsoft_dashboards-2026.1.2.dist-info/RECORD
